{
 "id": 19169,
 "title": "[Ecstasy Poem]",
 "date": {
  "submission": "2012-07-23T07:00:00.000Z",
  "experience": ""
 },
 "author": {
  "name": "Respondent 60",
  "gender": "Female",
  "weight": ""
 },
 "dose": [
  {
   "time": "0",
   "administration": "",
   "substance": "MDMA"
  }
 ],
 "report": [
  "",
  "Ecstasy",
  "Turning round I see, surprised,",
  "a large, round, living temple.",
  "I am here, part of it all,",
  "I am part of it all.",
  "I look at the world",
  "and the world looks back at me.",
  "I am not alone.",
  "This is Ecstasy.",
  "Standing, I feel. So tender",
  "and being held so tenderly.",
  "My sadness is like a soft bud",
  "velvet and moist,",
  "my tear a dew drop",
  "trembling on the tip of my nose.",
  "I am so happy to feel.",
  "This is Ecstasy",
  "We sing, we laugh, we share",
  "and most of all, we care.",
  "We let each other see",
  "the beauty inside",
  "without shame or anxiety.",
  "We're happy and free.",
  "This is Ecstasy.",
  "",
  "by an established professional English woman, written just after experiencing ecstasy for the first time with some close friends. The 'temple' was a yurt."
 ],
 "erowid": {
  "id": "97054",
  "citation": " Respondent 60. \"[Ecstasy Poem]: experience with MDMA (Ecstasy) (ID 97054)\". Erowid.org. Jul 23, 2012. erowid.org/exp/97054",
  "substance": "MDMA (Ecstasy)",
  "views": "959"
 }
}
